bolt2/__init__.py
bolt2/manager.py
bolt2/trade.py
bolt2/utils.py
bolt2/wrapper.py
ibkr_trade_ai-0.0.1.dist-info/METADATA
ibkr_trade_ai-0.0.1.dist-info/WHEEL
ibkr_trade_ai-0.0.1.dist-info/entry_points.txt
ibkr_trade_ai-0.0.1.dist-info/RECORD
