Metadata-Version: 2.4
Name: ibkr-trade-ai
Version: 0.0.1
Summary: IBKR Trade AI - Lightweight asyncio based trading library for Interactive Brokers.
Project-URL: Homepage, https://jayaprakash.net
Project-URL: Documentation, https://readthedocs.org
Project-URL: Repository, https://github.com/osjayaprakash/ibkr-trade-ai.git
Project-URL: Bug Tracker, https://github.com/osjayaprakash/ibkr-trade-ai/issues
Author-email: Jayaprakash Sundararaj <osjayaprakash@gmail.com>
Maintainer-email: Jayaprakash Sundararaj <osjayaprakash@gmail.com>
License-Expression: MIT
Keywords: AI,IBKR,Interactivebrokers,algo-trading,trading
Classifier: Development Status :: 2 - Pre-Alpha
Classifier: Intended Audience :: Developers
Classifier: License :: OSI Approved :: MIT License
Classifier: Natural Language :: English
Classifier: Operating System :: OS Independent
Classifier: Programming Language :: Python
Classifier: Programming Language :: Python :: 3.7
Requires-Python: >=3.9
Requires-Dist: diskcache
